easyrec/__init__.py
easyrec/blocks/__init__.py
easyrec/blocks/interaction.py
easyrec/blocks/nn.py
easyrec/models/__init__.py
easyrec/models/afm.py
easyrec/models/ccpm.py
easyrec/models/deep_crossing.py
easyrec/models/deepfm.py
easyrec/models/dssm.py
easyrec/models/ffm.py
easyrec/models/fm.py
easyrec/models/fnn.py
easyrec/models/lr.py
easyrec/models/mlp.py
easyrec/models/mmoe.py
easyrec/models/neumf.py
easyrec/models/nfm.py
easyrec/models/pnn.py
easyrec/models/wide_and_deep.py
easyrec_python-0.0.1.dist-info/LICENSE
easyrec_python-0.0.1.dist-info/METADATA
easyrec_python-0.0.1.dist-info/WHEEL
easyrec_python-0.0.1.dist-info/top_level.txt
easyrec_python-0.0.1.dist-info/RECORD
