Metadata-Version: 2.1
Name: easyrec-python
Version: 0.0.1
Summary: Easy-to-use implementations of well-known recommender system algorithms based on Python Tensorflow 2.
Home-page: https://github.com/xu-zhiwei/easyrec
Author: Zhiwei Xu
Author-email: zhiweixuchn@gmail.com
License: MIT License
Keywords: Recommender System; CTR Estimation
Platform: UNKNOWN
Classifier: Development Status :: 4 - Beta
Classifier: License :: OSI Approved :: MIT License
Classifier: Operating System :: OS Independent
Classifier: Programming Language :: Python :: 3
Classifier: Topic :: Utilities
License-File: LICENSE
